vesuvius/__init__.py
vesuvius/volume.py
vesuvius/configs/cubes.yaml
vesuvius/configs/scrolls.yaml
vesuvius/paths/__init__.py
vesuvius/paths/fetcher.py
vesuvius/paths/parser.py
vesuvius/paths/utils.py
vesuvius/setup/__init__.py
vesuvius/setup/accept_terms.py
vesuvius-0.7.1.dist-info/LICENSE
vesuvius-0.7.1.dist-info/METADATA
vesuvius-0.7.1.dist-info/WHEEL
vesuvius-0.7.1.dist-info/entry_points.txt
vesuvius-0.7.1.dist-info/top_level.txt
vesuvius-0.7.1.dist-info/RECORD
