Metadata-Version: 2.1
Name: vesuvius
Version: 0.7.1
Classifier: Programming Language :: Python :: 3
Classifier: License :: OSI Approved :: MIT License
Classifier: Operating System :: OS Independent
Requires-Python: >=3.8
License-File: LICENSE
Requires-Dist: numpy
Requires-Dist: requests
Requires-Dist: aiohttp
Requires-Dist: fsspec
Requires-Dist: tensorstore
Requires-Dist: zarr
Requires-Dist: tqdm
Requires-Dist: lxml
Requires-Dist: nest-asyncio
Requires-Dist: pynrrd
